{
    "status": 200,
    "data": [
        {
            "id": 230243398,
            "author": "dapperest",
            "vote": null,
            "album_cover": "oUtMknQ",
            "children": [
                {
                    "id": 230251108,
                    "author": "GrosslyIncandescent",
                    "vote": null,
                    "album_cover": "oUtMknQ",
                    "children": [
                        
                    ],
                    "downs": 0,
                    "author_id": 1853654,
                    "points": 47,
                    "on_album": true,
                    "datetime": 1400981787,
                    "ups": 47,
                    "comment": "Shouldn't he take you to dinner first?",
                    "deleted": false,
                    "image_id": "eptxq",
                    "parent_id": 230243398
                },
                {
                    "id": 230264167,
                    "author": "JScoT",
                    "vote": null,
                    "album_cover": "oUtMknQ",
                    "children": [
                        {
                            "id": 230294638,
                            "author": "ashmenon",
                            "vote": null,
                            "album_cover": "oUtMknQ",
                            "children": [
                                
                            ],
                            "downs": 0,
                            "author_id": 2758677,
                            "points": 9,
                            "on_album": true,
                            "datetime": 1400988228,
                            "ups": 9,
                            "comment": "Either way, it's about getting laid.",
                            "deleted": false,
                            "image_id": "eptxq",
                            "parent_id": 230264167
                        },
                        {
                            "id": 230267374,
                            "author": "CRAAAAAAAAAABS",
                            "vote": null,
                            "album_cover": "oUtMknQ",
                            "children": [
                                {
                                    "id": 230329786,
                                    "author": "thudrs",
                                    "vote": null,
                                    "album_cover": "oUtMknQ",
                                    "children": [
                                        
                                    ],
                                    "downs": 0,
                                    "author_id": 9838703,
                                    "points": 1,
                                    "on_album": true,
                                    "datetime": 1400993815,
                                    "ups": 1,
                                    "comment": "Because he can get CRAAAAAAAAAABS",
                                    "deleted": false,
                                    "image_id": "eptxq",
                                    "parent_id": 230267374
                                }
                            ],
                            "downs": 0,
                            "author_id": 6133716,
                            "points": 4,
                            "on_album": true,
                            "datetime": 1400984274,
                            "ups": 4,
                            "comment": "Why not both?",
                            "deleted": false,
                            "image_id": "eptxq",
                            "parent_id": 230264167
                        },
                        {
                            "id": 230388859,
                            "author": "vexavexa",
                            "vote": null,
                            "album_cover": "oUtMknQ",
                            "children": [
                                
                            ],
                            "downs": 0,
                            "author_id": 10941064,
                            "points": 2,
                            "on_album": true,
                            "datetime": 1401006061,
                            "ups": 2,
                            "comment": "Sexually. With tiles.",
                            "deleted": false,
                            "image_id": "eptxq",
                            "parent_id": 230264167
                        }
                    ],
                    "downs": 0,
                    "author_id": 4370912,
                    "points": 11,
                    "on_album": true,
                    "datetime": 1400983793,
                    "ups": 11,
                    "comment": "Like, sexually or with tiles?",
                    "deleted": false,
                    "image_id": "eptxq",
                    "parent_id": 230243398
                },
                {
                    "id": 230246461,
                    "author": "Graylinfaux",
                    "vote": null,
                    "album_cover": "oUtMknQ",
                    "children": [
                        {
                            "id": 230250763,
                            "author": "dapperest",
                            "vote": null,
                            "album_cover": "oUtMknQ",
                            "children": [
                                {
                                    "id": 230251249,
                                    "author": "Graylinfaux",
                                    "vote": null,
                                    "album_cover": "oUtMknQ",
                                    "children": [
                                        {
                                            "id": 230252128,
                                            "author": "dapperest",
                                            "vote": null,
                                            "album_cover": "oUtMknQ",
                                            "children": [
                                                {
                                                    "id": 230252380,
                                                    "author": "Graylinfaux",
                                                    "vote": null,
                                                    "album_cover": "oUtMknQ",
                                                    "children": [
                                                        {
                                                            "id": 230271271,
                                                            "author": "Ronmabot",
                                                            "vote": null,
                                                            "album_cover": "oUtMknQ",
                                                            "children": [
                                                                
                                                            ],
                                                            "downs": 0,
                                                            "author_id": 7850006,
                                                            "points": 2,
                                                            "on_album": true,
                                                            "datetime": 1400984835,
                                                            "ups": 2,
                                                            "comment": "Smooth",
                                                            "deleted": false,
                                                            "image_id": "eptxq",
                                                            "parent_id": 230252380
                                                        }
                                                    ],
                                                    "downs": 0,
                                                    "author_id": 6161381,
                                                    "points": 3,
                                                    "on_album": true,
                                                    "datetime": 1400981950,
                                                    "ups": 3,
                                                    "comment": "ALL ABOARD TO POUND TOWN! NEXT STOP YOUR ANUS!",
                                                    "deleted": false,
                                                    "image_id": "eptxq",
                                                    "parent_id": 230252128
                                                }
                                            ],
                                            "downs": 0,
                                            "author_id": 3406480,
                                            "points": 6,
                                            "on_album": true,
                                            "datetime": 1400981914,
                                            "ups": 6,
                                            "comment": "As long as they're BUSINESS SOCKS.  CAUSE IT'S BUSINESS TIME.",
                                            "deleted": false,
                                            "image_id": "eptxq",
                                            "parent_id": 230251249
                                        }
                                    ],
                                    "downs": 0,
                                    "author_id": 6161381,
                                    "points": 7,
                                    "on_album": true,
                                    "datetime": 1400981800,
                                    "ups": 7,
                                    "comment": "Alright can we settle for stockings? love me some stockings",
                                    "deleted": false,
                                    "image_id": "eptxq",
                                    "parent_id": 230250763
                                }
                            ],
                            "downs": 0,
                            "author_id": 3406480,
                            "points": 10,
                            "on_album": true,
                            "datetime": 1400981742,
                            "ups": 10,
                            "comment": "1. Tonight 2. Nothing, preferably 3. Not me.",
                            "deleted": false,
                            "image_id": "eptxq",
                            "parent_id": 230246461
                        }
                    ],
                    "downs": 2,
                    "author_id": 6161381,
                    "points": 14,
                    "on_album": true,
                    "datetime": 1400981124,
                    "ups": 16,
                    "comment": "when wear and who's on top?",
                    "deleted": false,
                    "image_id": "eptxq",
                    "parent_id": 230243398
                },
                {
                    "id": 230285638,
                    "author": "chrismofer",
                    "vote": null,
                    "album_cover": "oUtMknQ",
                    "children": [
                        
                    ],
                    "downs": 0,
                    "author_id": 1228056,
                    "points": 5,
                    "on_album": true,
                    "datetime": 1400986830,
                    "ups": 5,
                    "comment": "in the shower.",
                    "deleted": false,
                    "image_id": "eptxq",
                    "parent_id": 230243398
                },
                {
                    "id": 230246170,
                    "author": "cabals",
                    "vote": null,
                    "album_cover": "oUtMknQ",
                    "children": [
                        {
                            "id": 230250721,
                            "author": "Hujijiwatchi",
                            "vote": null,
                            "album_cover": "oUtMknQ",
                            "children": [
                                
                            ],
                            "downs": 1,
                            "author_id": 3645695,
                            "points": 1,
                            "on_album": true,
                            "datetime": 1400981736,
                            "ups": 2,
                            "comment": "senpai...",
                            "deleted": false,
                            "image_id": "eptxq",
                            "parent_id": 230246170
                        }
                    ],
                    "downs": 1,
                    "author_id": 1579006,
                    "points": 7,
                    "on_album": true,
                    "datetime": 1400981086,
                    "ups": 8,
                    "comment": "http://i.imgur.com/L39jBdr.gif",
                    "deleted": false,
                    "image_id": "eptxq",
                    "parent_id": 230243398
                },
                {
                    "id": 230255647,
                    "author": "gourami",
                    "vote": null,
                    "album_cover": "oUtMknQ",
                    "children": [
                        
                    ],
                    "downs": 0,
                    "author_id": 1517958,
                    "points": 2,
                    "on_album": true,
                    "datetime": 1400982414,
                    "ups": 2,
                    "comment": "subtle",
                    "deleted": false,
                    "image_id": "eptxq",
                    "parent_id": 230243398
                },
                {
                    "id": 230307517,
                    "author": "ElephantDildo",
                    "vote": null,
                    "album_cover": "oUtMknQ",
                    "children": [
                        
                    ],
                    "downs": 0,
                    "author_id": 3529902,
                    "points": 1,
                    "on_album": true,
                    "datetime": 1400990335,
                    "ups": 1,
                    "comment": "Hope you brought lube.",
                    "deleted": false,
                    "image_id": "eptxq",
                    "parent_id": 230243398
                },
                {
                    "id": 230296195,
                    "author": "Kevinnielsen",
                    "vote": null,
                    "album_cover": "oUtMknQ",
                    "children": [
                        
                    ],
                    "downs": 0,
                    "author_id": 1922747,
                    "points": 1,
                    "on_album": true,
                    "datetime": 1400988484,
                    "ups": 1,
                    "comment": "That was pretty straight forward..",
                    "deleted": false,
                    "image_id": "eptxq",
                    "parent_id": 230243398
                },
                {
                    "id": 230263033,
                    "author": "BoopBoopBeepBoop",
                    "vote": null,
                    "album_cover": "oUtMknQ",
                    "children": [
                        
                    ],
                    "downs": 3,
                    "author_id": 9695187,
                    "points": 0,
                    "on_album": true,
                    "datetime": 1400983605,
                    "ups": 3,
                    "comment": "Lewd",
                    "deleted": false,
                    "image_id": "eptxq",
                    "parent_id": 230243398
                }
            ],
            "downs": 3,
            "author_id": 3406480,
            "points": 218,
            "on_album": true,
            "datetime": 1400980698,
            "ups": 221,
            "comment": "Now do me.",
            "deleted": false,
            "image_id": "eptxq",
            "parent_id": 0
        },
        {
            "id": 230243278,
            "author": "Majorasshat",
            "vote": null,
            "album_cover": "oUtMknQ",
            "children": [
                {
                    "id": 230311912,
                    "author": "twostepsfromlost",
                    "vote": null,
                    "album_cover": "oUtMknQ",
                    "children": [
                        
                    ],
                    "downs": 0,
                    "author_id": 1293552,
                    "points": 4,
                    "on_album": true,
                    "datetime": 1400991028,
                    "ups": 4,
                    "comment": "Now he just needs jabba above his toilet with the caption \"bring me the poopie\"",
                    "deleted": false,
                    "image_id": "eptxq",
                    "parent_id": 230243278
                },
                {
                    "id": 230250808,
                    "author": "therooproject",
                    "vote": null,
                    "album_cover": "oUtMknQ",
                    "children": [
                        
                    ],
                    "downs": 0,
                    "author_id": 5992303,
                    "points": 2,
                    "on_album": true,
                    "datetime": 1400981747,
                    "ups": 2,
                    "comment": "Exactly what I thought. That's a badass custom job!",
                    "deleted": false,
                    "image_id": "eptxq",
                    "parent_id": 230243278
                },
                {
                    "id": 230249506,
                    "author": "CanadiansWillRule",
                    "vote": null,
                    "album_cover": "oUtMknQ",
                    "children": [
                        
                    ],
                    "downs": 0,
                    "author_id": 7833965,
                    "points": 1,
                    "on_album": true,
                    "datetime": 1400981560,
                    "ups": 1,
                    "comment": "I'm just thinking about if he'd have to redo it when he wants to sell the house... I'm such a worrywart",
                    "deleted": false,
                    "image_id": "eptxq",
                    "parent_id": 230243278
                }
            ],
            "downs": 2,
            "author_id": 5416482,
            "points": 104,
            "on_album": true,
            "datetime": 1400980679,
            "ups": 106,
            "comment": "That's pretty fucking neat",
            "deleted": false,
            "image_id": "eptxq",
            "parent_id": 0
        },
        {
            "id": 230244745,
            "author": "MUTGraphics",
            "vote": null,
            "album_cover": "oUtMknQ",
            "children": [
                {
                    "id": 230246674,
                    "author": "MUTGraphics",
                    "vote": null,
                    "album_cover": "oUtMknQ",
                    "children": [
                        
                    ],
                    "downs": 0,
                    "author_id": 6953648,
                    "points": 6,
                    "on_album": true,
                    "datetime": 1400981149,
                    "ups": 6,
                    "comment": "really tho",
                    "deleted": false,
                    "image_id": "eptxq",
                    "parent_id": 230244745
                }
            ],
            "downs": 0,
            "author_id": 6953648,
            "points": 27,
            "on_album": true,
            "datetime": 1400980883,
            "ups": 27,
            "comment": "Imagine doing it in this shower and having Mace Windu staring at you",
            "deleted": false,
            "image_id": "eptxq",
            "parent_id": 0
        },
        {
            "id": 230243200,
            "author": "SkittlesPower",
            "vote": null,
            "album_cover": "oUtMknQ",
            "children": [
                {
                    "id": 230245687,
                    "author": "JohnyRo",
                    "vote": null,
                    "album_cover": "oUtMknQ",
                    "children": [
                        {
                            "id": 230247622,
                            "author": "SkittlesPower",
                            "vote": null,
                            "album_cover": "oUtMknQ",
                            "children": [
                                
                            ],
                            "downs": 0,
                            "author_id": 6211406,
                            "points": 5,
                            "on_album": true,
                            "datetime": 1400981289,
                            "ups": 5,
                            "comment": "I did.",
                            "deleted": false,
                            "image_id": "eptxq",
                            "parent_id": 230245687
                        }
                    ],
                    "downs": 0,
                    "author_id": 9179736,
                    "points": 9,
                    "on_album": true,
                    "datetime": 1400981017,
                    "ups": 9,
                    "comment": "I bet you made those yourself you fucking overachiever!",
                    "deleted": false,
                    "image_id": "eptxq",
                    "parent_id": 230243200
                },
                {
                    "id": 230270716,
                    "author": "Doilooklikeacattoyaboy",
                    "vote": null,
                    "album_cover": "oUtMknQ",
                    "children": [
                        {
                            "id": 230371372,
                            "author": "youhadmeatmeattornado95",
                            "vote": null,
                            "album_cover": "oUtMknQ",
                            "children": [
                                
                            ],
                            "downs": 0,
                            "author_id": 10140142,
                            "points": 1,
                            "on_album": true,
                            "datetime": 1401001495,
                            "ups": 1,
                            "comment": "Igetthatreference.jpeg",
                            "deleted": false,
                            "image_id": "eptxq",
                            "parent_id": 230270716
                        }
                    ],
                    "downs": 0,
                    "author_id": 8212383,
                    "points": 7,
                    "on_album": true,
                    "datetime": 1400984762,
                    "ups": 7,
                    "comment": "Are you a deer?",
                    "deleted": false,
                    "image_id": "eptxq",
                    "parent_id": 230243200
                },
                {
                    "id": 230292385,
                    "author": "ChefSanji",
                    "vote": null,
                    "album_cover": "oUtMknQ",
                    "children": [
                        
                    ],
                    "downs": 0,
                    "author_id": 8183175,
                    "points": 2,
                    "on_album": true,
                    "datetime": 1400987874,
                    "ups": 2,
                    "comment": "I ate a chicken.",
                    "deleted": false,
                    "image_id": "eptxq",
                    "parent_id": 230243200
                },
                {
                    "id": 230356654,
                    "author": "KentAllard",
                    "vote": null,
                    "album_cover": "oUtMknQ",
                    "children": [
                        
                    ],
                    "downs": 2,
                    "author_id": 8625188,
                    "points": -1,
                    "on_album": true,
                    "datetime": 1400998569,
                    "ups": 1,
                    "comment": "Why is this comment getting so many upvotes!?!",
                    "deleted": false,
                    "image_id": "eptxq",
                    "parent_id": 230243200
                }
            ],
            "downs": 6,
            "author_id": 6211406,
            "points": 68,
            "on_album": true,
            "datetime": 1400980665,
            "ups": 74,
            "comment": "I ate a whole bunch of spagetti today. With turkey meatballs and shredded cheese. So there's that.",
            "deleted": false,
            "image_id": "eptxq",
            "parent_id": 0
        },
        {
            "id": 230249200,
            "author": "kileelee",
            "vote": null,
            "album_cover": "oUtMknQ",
            "children": [
                {
                    "id": 230295301,
                    "author": "honingdas",
                    "vote": null,
                    "album_cover": "oUtMknQ",
                    "children": [
                        
                    ],
                    "downs": 0,
                    "author_id": 2747901,
                    "points": 13,
                    "on_album": true,
                    "datetime": 1400988334,
                    "ups": 13,
                    "comment": "clear... as in nothing in the way.  buuuuut maybe glass doors would have been a tad classier",
                    "deleted": false,
                    "image_id": "eptxq",
                    "parent_id": 230249200
                },
                {
                    "id": 230390203,
                    "author": "jennanoelz",
                    "vote": null,
                    "album_cover": "oUtMknQ",
                    "children": [
                        {
                            "id": 230425741,
                            "author": "kileelee",
                            "vote": null,
                            "album_cover": "oUtMknQ",
                            "children": [
                                
                            ],
                            "downs": 0,
                            "author_id": 6946763,
                            "points": 2,
                            "on_album": true,
                            "datetime": 1401019207,
                            "ups": 2,
                            "comment": "Subway tiles are actually right on trend.",
                            "deleted": false,
                            "image_id": "eptxq",
                            "parent_id": 230390203
                        }
                    ],
                    "downs": 1,
                    "author_id": 6590231,
                    "points": 1,
                    "on_album": true,
                    "datetime": 1401006425,
                    "ups": 2,
                    "comment": "I'm sad the other tile is so horrible. Unless you are bathing in a subway.",
                    "deleted": false,
                    "image_id": "eptxq",
                    "parent_id": 230249200
                }
            ],
            "downs": 2,
            "author_id": 6946763,
            "points": 25,
            "on_album": true,
            "datetime": 1400981521,
            "ups": 27,
            "comment": "You did all of that and then hung a crappy shower curtain? ALL OF THAT?!?! *facepalm*",
            "deleted": false,
            "image_id": "eptxq",
            "parent_id": 0
        },
        {
            "id": 230243932,
            "author": "mssnarkyfish",
            "vote": null,
            "album_cover": "oUtMknQ",
            "children": [
                
            ],
            "downs": 0,
            "author_id": 1616261,
            "points": 9,
            "on_album": true,
            "datetime": 1400980769,
            "ups": 9,
            "comment": "This is amazing!",
            "deleted": false,
            "image_id": "eptxq",
            "parent_id": 0
        },
        {
            "id": 230295820,
            "author": "Scuum",
            "vote": null,
            "album_cover": "oUtMknQ",
            "children": [
                
            ],
            "downs": 1,
            "author_id": 7078214,
            "points": 12,
            "on_album": true,
            "datetime": 1400988421,
            "ups": 13,
            "comment": "Resale value -10%",
            "deleted": false,
            "image_id": "eptxq",
            "parent_id": 0
        },
        {
            "id": 230263885,
            "author": "unknown0user",
            "vote": null,
            "album_cover": "oUtMknQ",
            "children": [
                
            ],
            "downs": 1,
            "author_id": 7250426,
            "points": 7,
            "on_album": true,
            "datetime": 1400983753,
            "ups": 8,
            "comment": "Wow, so you really like Star Trek huh?",
            "deleted": false,
            "image_id": "eptxq",
            "parent_id": 0
        },
        {
            "id": 230243164,
            "author": "DoctorJungyBrongen",
            "vote": null,
            "album_cover": "oUtMknQ",
            "children": [
                
            ],
            "downs": 3,
            "author_id": 5977792,
            "points": 6,
            "on_album": true,
            "datetime": 1400980658,
            "ups": 9,
            "comment": "I should spend my time on more constructive things like this. Very cool!",
            "deleted": false,
            "image_id": "eptxq",
            "parent_id": 0
        },
        {
            "id": 230301016,
            "author": "hoggough",
            "vote": null,
            "album_cover": "oUtMknQ",
            "children": [
                
            ],
            "downs": 0,
            "author_id": 11227213,
            "points": 3,
            "on_album": true,
            "datetime": 1400989292,
            "ups": 3,
            "comment": "You had a perfectly good Star Trek Next Gen wall cover all ready",
            "deleted": false,
            "image_id": "eptxq",
            "parent_id": 0
        },
        {
            "id": 230269381,
            "author": "ANorthernGuy",
            "vote": null,
            "album_cover": "oUtMknQ",
            "children": [
                
            ],
            "downs": 0,
            "author_id": 6947345,
            "points": 3,
            "on_album": true,
            "datetime": 1400984562,
            "ups": 3,
            "comment": "This post made me so happy i don't know why. :)",
            "deleted": false,
            "image_id": "eptxq",
            "parent_id": 0
        },
        {
            "id": 230268898,
            "author": "jewbearE5",
            "vote": null,
            "album_cover": "oUtMknQ",
            "children": [
                {
                    "id": 230314561,
                    "author": "donutbomb",
                    "vote": null,
                    "album_cover": "oUtMknQ",
                    "children": [
                        
                    ],
                    "downs": 0,
                    "author_id": 7125605,
                    "points": 1,
                    "on_album": true,
                    "datetime": 1400991450,
                    "ups": 1,
                    "comment": "*Mandalore",
                    "deleted": false,
                    "image_id": "eptxq",
                    "parent_id": 230268898
                }
            ],
            "downs": 0,
            "author_id": 7275923,
            "points": 3,
            "on_album": true,
            "datetime": 1400984493,
            "ups": 3,
            "comment": "Boba Fett for President!",
            "deleted": false,
            "image_id": "eptxq",
            "parent_id": 0
        },
        {
            "id": 230252779,
            "author": "Witzelsucht",
            "vote": null,
            "album_cover": "oUtMknQ",
            "children": [
                {
                    "id": 230257213,
                    "author": "kungfuman",
                    "vote": null,
                    "album_cover": "oUtMknQ",
                    "children": [
                        {
                            "id": 230291320,
                            "author": "shumka",
                            "vote": null,
                            "album_cover": "oUtMknQ",
                            "children": [
                                {
                                    "id": 230361919,
                                    "author": "CapriciouslyConspicuous",
                                    "vote": null,
                                    "album_cover": "oUtMknQ",
                                    "children": [
                                        
                                    ],
                                    "downs": 0,
                                    "author_id": 7839137,
                                    "points": 2,
                                    "on_album": true,
                                    "datetime": 1400999562,
                                    "ups": 2,
                                    "comment": "Just eyeballing it it looks like the mosaic is a whole number of 'normal' tiles high so I think OP planned probably for it to be ripped out.",
                                    "deleted": false,
                                    "image_id": "eptxq",
                                    "parent_id": 230291320
                                }
                            ],
                            "downs": 0,
                            "author_id": 3073391,
                            "points": 5,
                            "on_album": true,
                            "datetime": 1400987696,
                            "ups": 5,
                            "comment": "Yah, this wouldn't be hard or that expensive to rip out for a resale. Live there for 10-20 years? Worth it.",
                            "deleted": false,
                            "image_id": "eptxq",
                            "parent_id": 230257213
                        }
                    ],
                    "downs": 0,
                    "author_id": 976294,
                    "points": 12,
                    "on_album": true,
                    "datetime": 1400982643,
                    "ups": 12,
                    "comment": "If you can't personalize your own home what can you personalize?",
                    "deleted": false,
                    "image_id": "eptxq",
                    "parent_id": 230252779
                }
            ],
            "downs": 6,
            "author_id": 3308542,
            "points": 5,
            "on_album": true,
            "datetime": 1400982007,
            "ups": 11,
            "comment": "In this post: learn how to hurt the resale value of your house through your dorky obsessions!",
            "deleted": false,
            "image_id": "eptxq",
            "parent_id": 0
        },
        {
            "id": 230254303,
            "author": "moxymox",
            "vote": null,
            "album_cover": "oUtMknQ",
            "children": [
                {
                    "id": 230266486,
                    "author": "StewPedasso",
                    "vote": null,
                    "album_cover": "oUtMknQ",
                    "children": [
                        
                    ],
                    "downs": 1,
                    "author_id": 1926594,
                    "points": 3,
                    "on_album": true,
                    "datetime": 1400984135,
                    "ups": 4,
                    "comment": "No, you're not.",
                    "deleted": false,
                    "image_id": "eptxq",
                    "parent_id": 230254303
                },
                {
                    "id": 230343133,
                    "author": "goonies4life",
                    "vote": null,
                    "album_cover": "oUtMknQ",
                    "children": [
                        {
                            "id": 230411005,
                            "author": "SassyVader",
                            "vote": null,
                            "album_cover": "oUtMknQ",
                            "children": [
                                
                            ],
                            "downs": 0,
                            "author_id": 4508837,
                            "points": 1,
                            "on_album": true,
                            "datetime": 1401013400,
                            "ups": 1,
                            "comment": "Said \"Goonies4life\" ...   ;)",
                            "deleted": false,
                            "image_id": "eptxq",
                            "parent_id": 230343133
                        }
                    ],
                    "downs": 1,
                    "author_id": 9871325,
                    "points": 1,
                    "on_album": true,
                    "datetime": 1400996300,
                    "ups": 2,
                    "comment": "I just think about how nice a bathroom this guy could make. Clearly the skills are there. Was this a shower for kids? It just seems odd.",
                    "deleted": false,
                    "image_id": "eptxq",
                    "parent_id": 230254303
                }
            ],
            "downs": 4,
            "author_id": 5646164,
            "points": 4,
            "on_album": true,
            "datetime": 1400982220,
            "ups": 8,
            "comment": "Ok... am I the only adult who doesn't want to be surrounded by corporate media franchises of my childhood?",
            "deleted": false,
            "image_id": "eptxq",
            "parent_id": 0
        },
        {
            "id": 230318962,
            "author": "shisno117",
            "vote": null,
            "album_cover": "oUtMknQ",
            "children": [
                
            ],
            "downs": 0,
            "author_id": 1934249,
            "points": 2,
            "on_album": true,
            "datetime": 1400992086,
            "ups": 2,
            "comment": "Years from now an archeologist will discover your shower and think, \"This is what life was like.\"",
            "deleted": false,
            "image_id": "eptxq",
            "parent_id": 0
        },
        {
            "id": 230311540,
            "author": "SometimesIsayfunnyshit",
            "vote": null,
            "album_cover": "oUtMknQ",
            "children": [
                {
                    "id": 230326264,
                    "author": "georgeAF1",
                    "vote": null,
                    "album_cover": "oUtMknQ",
                    "children": [
                        {
                            "id": 230406949,
                            "author": "kerms",
                            "vote": null,
                            "album_cover": "oUtMknQ",
                            "children": [
                                
                            ],
                            "downs": 0,
                            "author_id": 4433969,
                            "points": 1,
                            "on_album": true,
                            "datetime": 1401011893,
                            "ups": 1,
                            "comment": "I'm so glad every video on youtube has the speed option now.",
                            "deleted": false,
                            "image_id": "eptxq",
                            "parent_id": 230326264
                        }
                    ],
                    "downs": 0,
                    "author_id": 8998080,
                    "points": 1,
                    "on_album": true,
                    "datetime": 1400993263,
                    "ups": 1,
                    "comment": "https://www.youtube.com/watch?v=FWO5Ai_a80M",
                    "deleted": false,
                    "image_id": "eptxq",
                    "parent_id": 230311540
                }
            ],
            "downs": 0,
            "author_id": 7416305,
            "points": 2,
            "on_album": true,
            "datetime": 1400990964,
            "ups": 2,
            "comment": "Now whenever you shower you have to play the Cantina music in the background.",
            "deleted": false,
            "image_id": "eptxq",
            "parent_id": 0
        },
        {
            "id": 230298091,
            "author": "VictoriaLynnn",
            "vote": null,
            "album_cover": "oUtMknQ",
            "children": [
                
            ],
            "downs": 0,
            "author_id": 3416850,
            "points": 2,
            "on_album": true,
            "datetime": 1400988789,
            "ups": 2,
            "comment": "I actually love how nerdy grown-ass men and women are these days. It's amazing and inspirational.",
            "deleted": false,
            "image_id": "eptxq",
            "parent_id": 0
        },
        {
            "id": 230268208,
            "author": "cleverlydisguised",
            "vote": null,
            "album_cover": "oUtMknQ",
            "children": [
                
            ],
            "downs": 0,
            "author_id": 3798144,
            "points": 2,
            "on_album": true,
            "datetime": 1400984399,
            "ups": 2,
            "comment": "Thought the space saxophone dude was Johnny Bravo for a second.",
            "deleted": false,
            "image_id": "eptxq",
            "parent_id": 0
        },
        {
            "id": 230267815,
            "author": "UniqueEggLicker",
            "vote": null,
            "album_cover": "oUtMknQ",
            "children": [
                
            ],
            "downs": 0,
            "author_id": 5048781,
            "points": 2,
            "on_album": true,
            "datetime": 1400984342,
            "ups": 2,
            "comment": "This is really fucking rad holy shit.",
            "deleted": false,
            "image_id": "eptxq",
            "parent_id": 0
        },
        {
            "id": 230254288,
            "author": "DoverBoys",
            "vote": null,
            "album_cover": "oUtMknQ",
            "children": [
                
            ],
            "downs": 0,
            "author_id": 790152,
            "points": 2,
            "on_album": true,
            "datetime": 1400982218,
            "ups": 2,
            "comment": "I'm disappointed there's no pixel Jabba.",
            "deleted": false,
            "image_id": "eptxq",
            "parent_id": 0
        },
        {
            "id": 230253232,
            "author": "JPBStory",
            "vote": null,
            "album_cover": "oUtMknQ",
            "children": [
                
            ],
            "downs": 0,
            "author_id": 3019294,
            "points": 2,
            "on_album": true,
            "datetime": 1400982072,
            "ups": 2,
            "comment": "That's pretty cool but you better hope whoever you eventually sell your house to likes it.",
            "deleted": false,
            "image_id": "eptxq",
            "parent_id": 0
        },
        {
            "id": 230242321,
            "author": "MaxSawyer",
            "vote": null,
            "album_cover": "oUtMknQ",
            "children": [
                {
                    "id": 230243836,
                    "author": "NationalOrganizationOfMenAgainstAmazonianMasterhood",
                    "vote": null,
                    "album_cover": "oUtMknQ",
                    "children": [
                        {
                            "id": 230244043,
                            "author": "MaxSawyer",
                            "vote": null,
                            "album_cover": "oUtMknQ",
                            "children": [
                                
                            ],
                            "downs": 0,
                            "author_id": 9341964,
                            "points": 1,
                            "on_album": true,
                            "datetime": 1400980780,
                            "ups": 1,
                            "comment": "thanks buddy, it's another league..",
                            "deleted": false,
                            "image_id": "eptxq",
                            "parent_id": 230243836
                        }
                    ],
                    "downs": 0,
                    "author_id": 9334167,
                    "points": 2,
                    "on_album": true,
                    "datetime": 1400980754,
                    "ups": 2,
                    "comment": "Passed this, thought a moment.  Came back to upvote.  You deserve better.",
                    "deleted": false,
                    "image_id": "eptxq",
                    "parent_id": 230242321
                }
            ],
            "downs": 12,
            "author_id": 9341964,
            "points": 0,
            "on_album": true,
            "datetime": 1400980541,
            "ups": 12,
            "comment": "that's nice, honey.",
            "deleted": false,
            "image_id": "eptxq",
            "parent_id": 0
        },
        {
            "id": 230244541,
            "author": "MarkBuck",
            "vote": null,
            "album_cover": "oUtMknQ",
            "children": [
                {
                    "id": 230252887,
                    "author": "iamahorriblemonsterwhodeservesdeath",
                    "vote": null,
                    "album_cover": "oUtMknQ",
                    "children": [
                        {
                            "id": 230264572,
                            "author": "yourspellingisbadandyoushouldfeelbad",
                            "vote": null,
                            "album_cover": "oUtMknQ",
                            "children": [
                                
                            ],
                            "downs": 0,
                            "author_id": 6087914,
                            "points": 4,
                            "on_album": true,
                            "datetime": 1400983856,
                            "ups": 4,
                            "comment": "pretty sure there's a recently married couple on here who would be interested",
                            "deleted": false,
                            "image_id": "eptxq",
                            "parent_id": 230252887
                        }
                    ],
                    "downs": 0,
                    "author_id": 10400467,
                    "points": 3,
                    "on_album": true,
                    "datetime": 1400982022,
                    "ups": 3,
                    "comment": "Seriously. Talk about limiting your prospective buyers market.",
                    "deleted": false,
                    "image_id": "eptxq",
                    "parent_id": 230244541
                }
            ],
            "downs": 1,
            "author_id": 3088991,
            "points": 2,
            "on_album": true,
            "datetime": 1400980856,
            "ups": 3,
            "comment": "Great resale value!",
            "deleted": false,
            "image_id": "eptxq",
            "parent_id": 0
        },
        {
            "id": 230242903,
            "author": "ignishin",
            "vote": null,
            "album_cover": "oUtMknQ",
            "children": [
                
            ],
            "downs": 6,
            "author_id": 1064650,
            "points": 1,
            "on_album": true,
            "datetime": 1400980628,
            "ups": 7,
            "comment": "Looks good and all, but all the white and tiles make it look like you're showering in a prison.",
            "deleted": false,
            "image_id": "eptxq",
            "parent_id": 0
        },
        {
            "id": 230244787,
            "author": "claireconcept",
            "vote": null,
            "album_cover": "oUtMknQ",
            "children": [
                
            ],
            "downs": 1,
            "author_id": 3999087,
            "points": 1,
            "on_album": true,
            "datetime": 1400980886,
            "ups": 2,
            "comment": "I've asked my boyfriend for one. I would like Mario.",
            "deleted": false,
            "image_id": "eptxq",
            "parent_id": 0
        },
        {
            "id": 230447014,
            "author": "HouseMouseMN",
            "vote": null,
            "album_cover": "oUtMknQ",
            "children": [
                
            ],
            "downs": 0,
            "author_id": 8667440,
            "points": 1,
            "on_album": true,
            "datetime": 1401025805,
            "ups": 1,
            "comment": "Give me your address. I want to shower there with Theme music in background! I'll bring soap. This is wayyyyy cool!!!!",
            "deleted": false,
            "image_id": "eptxq",
            "parent_id": 0
        },
        {
            "id": 230440597,
            "author": "polica",
            "vote": null,
            "album_cover": "oUtMknQ",
            "children": [
                
            ],
            "downs": 0,
            "author_id": 10997635,
            "points": 1,
            "on_album": true,
            "datetime": 1401024254,
            "ups": 1,
            "comment": "As someone who knows how to lay tiles I can appreciate all the hard work and effort that went into this. Wonderful job!",
            "deleted": false,
            "image_id": "eptxq",
            "parent_id": 0
        },
        {
            "id": 230425918,
            "author": "miiq",
            "vote": null,
            "album_cover": "oUtMknQ",
            "children": [
                
            ],
            "downs": 0,
            "author_id": 1923328,
            "points": 1,
            "on_album": true,
            "datetime": 1401019282,
            "ups": 1,
            "comment": "This is awesome",
            "deleted": false,
            "image_id": "eptxq",
            "parent_id": 0
        },
        {
            "id": 230418091,
            "author": "bigbananarama",
            "vote": null,
            "album_cover": "oUtMknQ",
            "children": [
                
            ],
            "downs": 0,
            "author_id": 2674861,
            "points": 1,
            "on_album": true,
            "datetime": 1401016195,
            "ups": 1,
            "comment": "Dude, this is the sickest DIY shit I've ever seen on here! Excellent work!",
            "deleted": false,
            "image_id": "eptxq",
            "parent_id": 0
        },
        {
            "id": 230407051,
            "author": "welcomestranger",
            "vote": null,
            "album_cover": "oUtMknQ",
            "children": [
                
            ],
            "downs": 0,
            "author_id": 3613378,
            "points": 1,
            "on_album": true,
            "datetime": 1401011930,
            "ups": 1,
            "comment": "Great work! But RotJ Fett needs to have the red gauntlets not the green...",
            "deleted": false,
            "image_id": "eptxq",
            "parent_id": 0
        },
        {
            "id": 230405737,
            "author": "Babs237",
            "vote": null,
            "album_cover": "oUtMknQ",
            "children": [
                
            ],
            "downs": 0,
            "author_id": 9829166,
            "points": 1,
            "on_album": true,
            "datetime": 1401011472,
            "ups": 1,
            "comment": "That's an awesome work! xxx",
            "deleted": false,
            "image_id": "eptxq",
            "parent_id": 0
        },
        {
            "id": 230404756,
            "author": "penguinsrulez",
            "vote": null,
            "album_cover": "oUtMknQ",
            "children": [
                
            ],
            "downs": 0,
            "author_id": 460841,
            "points": 1,
            "on_album": true,
            "datetime": 1401011153,
            "ups": 1,
            "comment": "it looks like Darth Sidious is getting anal",
            "deleted": false,
            "image_id": "eptxq",
            "parent_id": 0
        },
        {
            "id": 230383984,
            "author": "handsMoleman",
            "vote": null,
            "album_cover": "oUtMknQ",
            "children": [
                
            ],
            "downs": 0,
            "author_id": 10691557,
            "points": 1,
            "on_album": true,
            "datetime": 1401004726,
            "ups": 1,
            "comment": "Super inspiring! Well done! I'm off to clean my bath",
            "deleted": false,
            "image_id": "eptxq",
            "parent_id": 0
        },
        {
            "id": 230376811,
            "author": "khitikat",
            "vote": null,
            "album_cover": "oUtMknQ",
            "children": [
                
            ],
            "downs": 0,
            "author_id": 6098780,
            "points": 1,
            "on_album": true,
            "datetime": 1401002828,
            "ups": 1,
            "comment": "Looks like images from the game tiny death star",
            "deleted": false,
            "image_id": "eptxq",
            "parent_id": 0
        },
        {
            "id": 230348878,
            "author": "Blacksuami",
            "vote": null,
            "album_cover": "oUtMknQ",
            "children": [
                
            ],
            "downs": 0,
            "author_id": 11388109,
            "points": 1,
            "on_album": true,
            "datetime": 1400997299,
            "ups": 1,
            "comment": "I'm so going to use those skins in Risk of Rain.",
            "deleted": false,
            "image_id": "eptxq",
            "parent_id": 0
        },
        {
            "id": 230344393,
            "author": "The8obman",
            "vote": null,
            "album_cover": "oUtMknQ",
            "children": [
                
            ],
            "downs": 0,
            "author_id": 6057986,
            "points": 1,
            "on_album": true,
            "datetime": 1400996551,
            "ups": 1,
            "comment": "don't act like you're not going to wack it to to pixelated slave-Leia, OP",
            "deleted": false,
            "image_id": "eptxq",
            "parent_id": 0
        },
        {
            "id": 230326570,
            "author": "georgeAF1",
            "vote": null,
            "album_cover": "oUtMknQ",
            "children": [
                
            ],
            "downs": 0,
            "author_id": 8998080,
            "points": 1,
            "on_album": true,
            "datetime": 1400993321,
            "ups": 1,
            "comment": "https://www.youtube.com/watch?v=FWO5Ai_a80M",
            "deleted": false,
            "image_id": "eptxq",
            "parent_id": 0
        },
        {
            "id": 230318014,
            "author": "soundslikeapersonalproblem",
            "vote": null,
            "album_cover": "oUtMknQ",
            "children": [
                
            ],
            "downs": 0,
            "author_id": 4520387,
            "points": 1,
            "on_album": true,
            "datetime": 1400991945,
            "ups": 1,
            "comment": "really awesome!",
            "deleted": false,
            "image_id": "eptxq",
            "parent_id": 0
        },
        {
            "id": 230316229,
            "author": "Chargers220",
            "vote": null,
            "album_cover": "oUtMknQ",
            "children": [
                
            ],
            "downs": 0,
            "author_id": 1867547,
            "points": 1,
            "on_album": true,
            "datetime": 1400991699,
            "ups": 1,
            "comment": "I love you.",
            "deleted": false,
            "image_id": "eptxq",
            "parent_id": 0
        },
        {
            "id": 230312365,
            "author": "tarataqa",
            "vote": null,
            "album_cover": "oUtMknQ",
            "children": [
                
            ],
            "downs": 0,
            "author_id": 155843,
            "points": 1,
            "on_album": true,
            "datetime": 1400991100,
            "ups": 1,
            "comment": "Holy shit; this is badass! +1 for IG-88 and even an ugnaught!",
            "deleted": false,
            "image_id": "eptxq",
            "parent_id": 0
        },
        {
            "id": 230310925,
            "author": "carhop",
            "vote": null,
            "album_cover": "oUtMknQ",
            "children": [
                
            ],
            "downs": 0,
            "author_id": 8895858,
            "points": 1,
            "on_album": true,
            "datetime": 1400990860,
            "ups": 1,
            "comment": "pew pew pew",
            "deleted": false,
            "image_id": "eptxq",
            "parent_id": 0
        },
        {
            "id": 230303359,
            "author": "Idonthavealottosay",
            "vote": null,
            "album_cover": "oUtMknQ",
            "children": [
                
            ],
            "downs": 0,
            "author_id": 8795885,
            "points": 1,
            "on_album": true,
            "datetime": 1400989688,
            "ups": 1,
            "comment": "Too impressive!",
            "deleted": false,
            "image_id": "eptxq",
            "parent_id": 0
        },
        {
            "id": 230300434,
            "author": "smellybug",
            "vote": null,
            "album_cover": "oUtMknQ",
            "children": [
                
            ],
            "downs": 0,
            "author_id": 3000159,
            "points": 1,
            "on_album": true,
            "datetime": 1400989199,
            "ups": 1,
            "comment": "That's awesum. Wanna copy. Wife would never allow it. Sad now.",
            "deleted": false,
            "image_id": "eptxq",
            "parent_id": 0
        },
        {
            "id": 230294740,
            "author": "ashmenon",
            "vote": null,
            "album_cover": "oUtMknQ",
            "children": [
                
            ],
            "downs": 0,
            "author_id": 2758677,
            "points": 1,
            "on_album": true,
            "datetime": 1400988245,
            "ups": 1,
            "comment": "Your tiles aren't the only things that want to get laid.",
            "deleted": false,
            "image_id": "eptxq",
            "parent_id": 0
        },
        {
            "id": 230289844,
            "author": "poodiggah",
            "vote": null,
            "album_cover": "oUtMknQ",
            "children": [
                
            ],
            "downs": 0,
            "author_id": 8196219,
            "points": 1,
            "on_album": true,
            "datetime": 1400987474,
            "ups": 1,
            "comment": "McPixel!",
            "deleted": false,
            "image_id": "eptxq",
            "parent_id": 0
        },
        {
            "id": 230280907,
            "author": "scarabrae",
            "vote": null,
            "album_cover": "oUtMknQ",
            "children": [
                
            ],
            "downs": 0,
            "author_id": 4442216,
            "points": 1,
            "on_album": true,
            "datetime": 1400986195,
            "ups": 1,
            "comment": "That's a hell of a lot of work.  I think the grout is the visual killer here, though.",
            "deleted": false,
            "image_id": "eptxq",
            "parent_id": 0
        },
        {
            "id": 230278324,
            "author": "Gingrbreadmann",
            "vote": null,
            "album_cover": "oUtMknQ",
            "children": [
                {
                    "id": 230278528,
                    "author": "Gingrbreadmann",
                    "vote": null,
                    "album_cover": "oUtMknQ",
                    "children": [
                        
                    ],
                    "downs": 0,
                    "author_id": 9576075,
                    "points": 1,
                    "on_album": true,
                    "datetime": 1400985873,
                    "ups": 1,
                    "comment": "I'LL LET YOU BE HAN!!..",
                    "deleted": false,
                    "image_id": "eptxq",
                    "parent_id": 230278324
                }
            ],
            "downs": 0,
            "author_id": 9576075,
            "points": 1,
            "on_album": true,
            "datetime": 1400985844,
            "ups": 1,
            "comment": "OP wanna take a shower?",
            "deleted": false,
            "image_id": "eptxq",
            "parent_id": 0
        },
        {
            "id": 230275315,
            "author": "gentlemansnowman",
            "vote": null,
            "album_cover": "oUtMknQ",
            "children": [
                
            ],
            "downs": 0,
            "author_id": 10411138,
            "points": 1,
            "on_album": true,
            "datetime": 1400985387,
            "ups": 1,
            "comment": "I bet it makes fapping in the shower 10x faster",
            "deleted": false,
            "image_id": "eptxq",
            "parent_id": 0
        },
        {
            "id": 230272552,
            "author": "Shalhavet",
            "vote": null,
            "album_cover": "oUtMknQ",
            "children": [
                
            ],
            "downs": 0,
            "author_id": 283343,
            "points": 1,
            "on_album": true,
            "datetime": 1400985011,
            "ups": 1,
            "comment": "I though those were Chiclets...",
            "deleted": false,
            "image_id": "eptxq",
            "parent_id": 0
        },
        {
            "id": 230272303,
            "author": "Derpidoop",
            "vote": null,
            "album_cover": "oUtMknQ",
            "children": [
                
            ],
            "downs": 0,
            "author_id": 11341972,
            "points": 1,
            "on_album": true,
            "datetime": 1400984981,
            "ups": 1,
            "comment": "And then you have a girl who needs to shower and you show her the other bathroom",
            "deleted": false,
            "image_id": "eptxq",
            "parent_id": 0
        },
        {
            "id": 230271550,
            "author": "fartharder",
            "vote": null,
            "album_cover": "oUtMknQ",
            "children": [
                
            ],
            "downs": 0,
            "author_id": 213342,
            "points": 1,
            "on_album": true,
            "datetime": 1400984872,
            "ups": 1,
            "comment": "Wow.",
            "deleted": false,
            "image_id": "eptxq",
            "parent_id": 0
        },
        {
            "id": 230267494,
            "author": "thereareonlytwothingsinthisworldicantstand",
            "vote": null,
            "album_cover": "oUtMknQ",
            "children": [
                
            ],
            "downs": 0,
            "author_id": 3243455,
            "points": 1,
            "on_album": true,
            "datetime": 1400984295,
            "ups": 1,
            "comment": "I too spent a great deal of time in the bathroom.  As a porcelain bench warmer.",
            "deleted": false,
            "image_id": "eptxq",
            "parent_id": 0
        },
        {
            "id": 230267338,
            "author": "frankprilljr",
            "vote": null,
            "album_cover": "oUtMknQ",
            "children": [
                
            ],
            "downs": 0,
            "author_id": 3334462,
            "points": 1,
            "on_album": true,
            "datetime": 1400984271,
            "ups": 1,
            "comment": "This is the greatest thing in the world",
            "deleted": false,
            "image_id": "eptxq",
            "parent_id": 0
        },
        {
            "id": 230266159,
            "author": "StewPedasso",
            "vote": null,
            "album_cover": "oUtMknQ",
            "children": [
                
            ],
            "downs": 0,
            "author_id": 1926594,
            "points": 1,
            "on_album": true,
            "datetime": 1400984087,
            "ups": 1,
            "comment": "I can fold an origami crane.",
            "deleted": false,
            "image_id": "eptxq",
            "parent_id": 0
        },
        {
            "id": 230260876,
            "author": "Scrappytonya",
            "vote": null,
            "album_cover": "oUtMknQ",
            "children": [
                
            ],
            "downs": 0,
            "author_id": 5579295,
            "points": 1,
            "on_album": true,
            "datetime": 1400983247,
            "ups": 1,
            "comment": "Awesome.",
            "deleted": false,
            "image_id": "eptxq",
            "parent_id": 0
        },
        {
            "id": 230260447,
            "author": "DenimBeard",
            "vote": null,
            "album_cover": "oUtMknQ",
            "children": [
                
            ],
            "downs": 0,
            "author_id": 3034839,
            "points": 1,
            "on_album": true,
            "datetime": 1400983175,
            "ups": 1,
            "comment": "Sex bench",
            "deleted": false,
            "image_id": "eptxq",
            "parent_id": 0
        },
        {
            "id": 230259256,
            "author": "Verskaizi",
            "vote": null,
            "album_cover": "oUtMknQ",
            "children": [
                
            ],
            "downs": 0,
            "author_id": 8363013,
            "points": 1,
            "on_album": true,
            "datetime": 1400982984,
            "ups": 1,
            "comment": "Install a speaker system in there where it plays the Star Wars cantina song and turn it on when you shower.",
            "deleted": false,
            "image_id": "eptxq",
            "parent_id": 0
        },
        {
            "id": 230258641,
            "author": "innocenceprovesnothing",
            "vote": null,
            "album_cover": "oUtMknQ",
            "children": [
                
            ],
            "downs": 0,
            "author_id": 8000365,
            "points": 1,
            "on_album": true,
            "datetime": 1400982887,
            "ups": 1,
            "comment": "tiler the creator",
            "deleted": false,
            "image_id": "eptxq",
            "parent_id": 0
        },
        {
            "id": 230252617,
            "author": "Budnoob",
            "vote": null,
            "album_cover": "oUtMknQ",
            "children": [
                
            ],
            "downs": 0,
            "author_id": 8466062,
            "points": 1,
            "on_album": true,
            "datetime": 1400981987,
            "ups": 1,
            "comment": "These aren't the pixels you are looking for",
            "deleted": false,
            "image_id": "eptxq",
            "parent_id": 0
        },
        {
            "id": 230251594,
            "author": "DanThePropMan",
            "vote": null,
            "album_cover": "oUtMknQ",
            "children": [
                
            ],
            "downs": 0,
            "author_id": 1249005,
            "points": 1,
            "on_album": true,
            "datetime": 1400981847,
            "ups": 1,
            "comment": "God damn, I need a shower with a seat. I physically cannot stand barefoot due to health issues. :(",
            "deleted": false,
            "image_id": "eptxq",
            "parent_id": 0
        },
        {
            "id": 230247586,
            "author": "TechnicolorDalek",
            "vote": null,
            "album_cover": "oUtMknQ",
            "children": [
                
            ],
            "downs": 0,
            "author_id": 11299207,
            "points": 1,
            "on_album": true,
            "datetime": 1400981285,
            "ups": 1,
            "comment": "the ass was fat",
            "deleted": false,
            "image_id": "eptxq",
            "parent_id": 0
        },
        {
            "id": 230246338,
            "author": "joedotcom",
            "vote": null,
            "album_cover": "oUtMknQ",
            "children": [
                
            ],
            "downs": 0,
            "author_id": 756277,
            "points": 1,
            "on_album": true,
            "datetime": 1400981112,
            "ups": 1,
            "comment": "This right here.... fucking awesome!  Good job!",
            "deleted": false,
            "image_id": "eptxq",
            "parent_id": 0
        },
        {
            "id": 230245498,
            "author": "HarryTheCaveman",
            "vote": null,
            "album_cover": "oUtMknQ",
            "children": [
                {
                    "id": 230252761,
                    "author": "cackcrusher",
                    "vote": null,
                    "album_cover": "oUtMknQ",
                    "children": [
                        
                    ],
                    "downs": 0,
                    "author_id": 10078918,
                    "points": 2,
                    "on_album": true,
                    "datetime": 1400982006,
                    "ups": 2,
                    "comment": "it's easier to aim at your mouth to drink your piss while sitting. Less spillage.",
                    "deleted": false,
                    "image_id": "eptxq",
                    "parent_id": 230245498
                },
                {
                    "id": 230271241,
                    "author": "fishnugget",
                    "vote": null,
                    "album_cover": "oUtMknQ",
                    "children": [
                        
                    ],
                    "downs": 0,
                    "author_id": 3276058,
                    "points": 1,
                    "on_album": true,
                    "datetime": 1400984831,
                    "ups": 1,
                    "comment": "To put your beer on",
                    "deleted": false,
                    "image_id": "eptxq",
                    "parent_id": 230245498
                },
                {
                    "id": 230265433,
                    "author": "yourspellingisbadandyoushouldfeelbad",
                    "vote": null,
                    "album_cover": "oUtMknQ",
                    "children": [
                        
                    ],
                    "downs": 0,
                    "author_id": 6087914,
                    "points": 1,
                    "on_album": true,
                    "datetime": 1400983977,
                    "ups": 1,
                    "comment": "For contemplating life",
                    "deleted": false,
                    "image_id": "eptxq",
                    "parent_id": 230245498
                },
                {
                    "id": 230252737,
                    "author": "chicky82",
                    "vote": null,
                    "album_cover": "oUtMknQ",
                    "children": [
                        
                    ],
                    "downs": 0,
                    "author_id": 3316739,
                    "points": 1,
                    "on_album": true,
                    "datetime": 1400982002,
                    "ups": 1,
                    "comment": "If there is a female who uses it, seats are handy to put your legs up on to shave.",
                    "deleted": false,
                    "image_id": "eptxq",
                    "parent_id": 230245498
                },
                {
                    "id": 230249617,
                    "author": "kileelee",
                    "vote": null,
                    "album_cover": "oUtMknQ",
                    "children": [
                        
                    ],
                    "downs": 0,
                    "author_id": 6946763,
                    "points": 1,
                    "on_album": true,
                    "datetime": 1400981575,
                    "ups": 1,
                    "comment": "For when you want to sit down and wash your feet...?",
                    "deleted": false,
                    "image_id": "eptxq",
                    "parent_id": 230245498
                }
            ],
            "downs": 0,
            "author_id": 6845018,
            "points": 1,
            "on_album": true,
            "datetime": 1400980988,
            "ups": 1,
            "comment": "This is super awesome, but why would you have a seat in a shower!? /serious question",
            "deleted": false,
            "image_id": "eptxq",
            "parent_id": 0
        },
        {
            "id": 230245063,
            "author": "MakingUpAUsernameIsTerrifying",
            "vote": null,
            "album_cover": "oUtMknQ",
            "children": [
                
            ],
            "downs": 0,
            "author_id": 1297308,
            "points": 1,
            "on_album": true,
            "datetime": 1400980928,
            "ups": 1,
            "comment": "For when you need to take a huge Sith.",
            "deleted": false,
            "image_id": "eptxq",
            "parent_id": 0
        },
        {
            "id": 230362780,
            "author": "MetalordPheonix",
            "vote": null,
            "album_cover": "oUtMknQ",
            "children": [
                
            ],
            "downs": 1,
            "author_id": 10687162,
            "points": 0,
            "on_album": true,
            "datetime": 1400999708,
            "ups": 1,
            "comment": "I feel the urge to make an Aperture Science themed bathroom with this intensifying.",
            "deleted": false,
            "image_id": "eptxq",
            "parent_id": 0
        },
        {
            "id": 230341480,
            "author": "alittlemorequiet",
            "vote": null,
            "album_cover": "oUtMknQ",
            "children": [
                
            ],
            "downs": 1,
            "author_id": 6658235,
            "points": 0,
            "on_album": true,
            "datetime": 1400995986,
            "ups": 1,
            "comment": "Please tell me you didn't use the Elmer's glue we all used in kindergarten.",
            "deleted": false,
            "image_id": "eptxq",
            "parent_id": 0
        }
    ],
    "success": true
}