{
    "status": 200,
    "data": [
        {
            "id": 229788985,
            "author": "andonRT",
            "vote": null,
            "album_cover": null,
            "children": [
                {
                    "id": 229909456,
                    "author": "HappinessIsStrange",
                    "vote": null,
                    "album_cover": null,
                    "children": [
                        {
                            "id": 230166706,
                            "author": "AlmostHuman2",
                            "vote": null,
                            "album_cover": null,
                            "children": [
                                
                            ],
                            "downs": 0,
                            "author_id": 10488571,
                            "points": 1,
                            "on_album": false,
                            "datetime": 1400968131,
                            "ups": 1,
                            "comment": "you stole my line",
                            "deleted": false,
                            "image_id": "iG1kk7a",
                            "parent_id": 229909456
                        }
                    ],
                    "downs": 0,
                    "author_id": 7179641,
                    "points": 27,
                    "on_album": false,
                    "datetime": 1400912492,
                    "ups": 27,
                    "comment": "Challenge to use words to describe accepted: A corgi waltzing with a platypus.",
                    "deleted": false,
                    "image_id": "iG1kk7a",
                    "parent_id": 229788985
                },
                {
                    "id": 229962517,
                    "author": "SunneyTehBunney",
                    "vote": null,
                    "album_cover": null,
                    "children": [
                        
                    ],
                    "downs": 0,
                    "author_id": 3848740,
                    "points": 6,
                    "on_album": false,
                    "datetime": 1400926734,
                    "ups": 6,
                    "comment": "Can you even?",
                    "deleted": false,
                    "image_id": "iG1kk7a",
                    "parent_id": 229788985
                },
                {
                    "id": 229807477,
                    "author": "shutterErv",
                    "vote": null,
                    "album_cover": null,
                    "children": [
                        
                    ],
                    "downs": 0,
                    "author_id": 8207727,
                    "points": 2,
                    "on_album": false,
                    "datetime": 1400895708,
                    "ups": 2,
                    "comment": "I start with that it is glorious",
                    "deleted": false,
                    "image_id": "iG1kk7a",
                    "parent_id": 229788985
                },
                {
                    "id": 229947193,
                    "author": "Necacal",
                    "vote": null,
                    "album_cover": null,
                    "children": [
                        
                    ],
                    "downs": 1,
                    "author_id": 11756167,
                    "points": 2,
                    "on_album": false,
                    "datetime": 1400921529,
                    "ups": 3,
                    "comment": "A corgi waltzing with a platypus",
                    "deleted": false,
                    "image_id": "iG1kk7a",
                    "parent_id": 229788985
                },
                {
                    "id": 229913569,
                    "author": "IamFartacus",
                    "vote": null,
                    "album_cover": null,
                    "children": [
                        
                    ],
                    "downs": 0,
                    "author_id": 3913779,
                    "points": 1,
                    "on_album": false,
                    "datetime": 1400913311,
                    "ups": 1,
                    "comment": "Verily-so wondrous an act as a Corgi and Platypus waltzing is befit only by the finest of prose, or no utterance at all. Waltz on, Corgipus.",
                    "deleted": false,
                    "image_id": "iG1kk7a",
                    "parent_id": 229788985
                }
            ],
            "downs": 2,
            "author_id": 9889079,
            "points": 324,
            "on_album": false,
            "datetime": 1400892910,
            "ups": 326,
            "comment": "That... Oh my god. Words cannot describe.",
            "deleted": false,
            "image_id": "iG1kk7a",
            "parent_id": 0
        },
        {
            "id": 229800775,
            "author": "p30n13s",
            "vote": null,
            "album_cover": null,
            "children": [
                {
                    "id": 229953967,
                    "author": "quickhand",
                    "vote": null,
                    "album_cover": null,
                    "children": [
                        
                    ],
                    "downs": 0,
                    "author_id": 8359392,
                    "points": 5,
                    "on_album": false,
                    "datetime": 1400923696,
                    "ups": 5,
                    "comment": "duck-billed fabupus",
                    "deleted": false,
                    "image_id": "iG1kk7a",
                    "parent_id": 229800775
                },
                {
                    "id": 229978618,
                    "author": "kungfuman",
                    "vote": null,
                    "album_cover": null,
                    "children": [
                        
                    ],
                    "downs": 0,
                    "author_id": 976294,
                    "points": 1,
                    "on_album": false,
                    "datetime": 1400932610,
                    "ups": 1,
                    "comment": "So classy too.",
                    "deleted": false,
                    "image_id": "iG1kk7a",
                    "parent_id": 229800775
                }
            ],
            "downs": 1,
            "author_id": 11592838,
            "points": 134,
            "on_album": false,
            "datetime": 1400894754,
            "ups": 135,
            "comment": "platypus is fabulous!...",
            "deleted": false,
            "image_id": "iG1kk7a",
            "parent_id": 0
        },
        {
            "id": 229790278,
            "author": "triciabunny",
            "vote": null,
            "album_cover": null,
            "children": [
                {
                    "id": 229910011,
                    "author": "PiiCii",
                    "vote": null,
                    "album_cover": null,
                    "children": [
                        {
                            "id": 229953874,
                            "author": "iamthemachine",
                            "vote": null,
                            "album_cover": null,
                            "children": [
                                
                            ],
                            "downs": 0,
                            "author_id": 1426266,
                            "points": 3,
                            "on_album": false,
                            "datetime": 1400923670,
                            "ups": 3,
                            "comment": "and that little curl in it too!",
                            "deleted": false,
                            "image_id": "iG1kk7a",
                            "parent_id": 229910011
                        }
                    ],
                    "downs": 0,
                    "author_id": 3258967,
                    "points": 6,
                    "on_album": false,
                    "datetime": 1400912600,
                    "ups": 6,
                    "comment": "That hair!",
                    "deleted": false,
                    "image_id": "iG1kk7a",
                    "parent_id": 229790278
                }
            ],
            "downs": 1,
            "author_id": 10106680,
            "points": 80,
            "on_album": false,
            "datetime": 1400893139,
            "ups": 81,
            "comment": "That is one fantastically dapper Corgi.",
            "deleted": false,
            "image_id": "iG1kk7a",
            "parent_id": 0
        },
        {
            "id": 229788898,
            "author": "artests",
            "vote": null,
            "album_cover": null,
            "children": [
                
            ],
            "downs": 0,
            "author_id": 11078134,
            "points": 23,
            "on_album": false,
            "datetime": 1400892897,
            "ups": 23,
            "comment": "I love it! :3",
            "deleted": false,
            "image_id": "iG1kk7a",
            "parent_id": 0
        },
        {
            "id": 229860028,
            "author": "wasd999",
            "vote": null,
            "album_cover": null,
            "children": [
                {
                    "id": 230162224,
                    "author": "AlmostHuman2",
                    "vote": null,
                    "album_cover": null,
                    "children": [
                        
                    ],
                    "downs": 0,
                    "author_id": 10488571,
                    "points": 2,
                    "on_album": false,
                    "datetime": 1400967412,
                    "ups": 2,
                    "comment": "indeed",
                    "deleted": false,
                    "image_id": "iG1kk7a",
                    "parent_id": 229860028
                }
            ],
            "downs": 0,
            "author_id": 5985745,
            "points": 16,
            "on_album": false,
            "datetime": 1400903836,
            "ups": 16,
            "comment": "@AlmostHuman2 he delivered",
            "deleted": false,
            "image_id": "iG1kk7a",
            "parent_id": 0
        },
        {
            "id": 229789651,
            "author": "dkdao",
            "vote": null,
            "album_cover": null,
            "children": [
                
            ],
            "downs": 1,
            "author_id": 3774117,
            "points": 16,
            "on_album": false,
            "datetime": 1400893023,
            "ups": 17,
            "comment": "What do I think? I think you've got some front-page material here, buddy!",
            "deleted": false,
            "image_id": "iG1kk7a",
            "parent_id": 0
        },
        {
            "id": 229798126,
            "author": "applewho",
            "vote": null,
            "album_cover": null,
            "children": [
                
            ],
            "downs": 0,
            "author_id": 6184424,
            "points": 10,
            "on_album": false,
            "datetime": 1400894377,
            "ups": 10,
            "comment": "This delivery... I like it! Another!",
            "deleted": false,
            "image_id": "iG1kk7a",
            "parent_id": 0
        },
        {
            "id": 229794664,
            "author": "Jumpinjackieflash",
            "vote": null,
            "album_cover": null,
            "children": [
                
            ],
            "downs": 0,
            "author_id": 8431067,
            "points": 5,
            "on_album": false,
            "datetime": 1400893853,
            "ups": 5,
            "comment": "He's dippin' her.",
            "deleted": false,
            "image_id": "iG1kk7a",
            "parent_id": 0
        },
        {
            "id": 229790485,
            "author": "Tzaot",
            "vote": null,
            "album_cover": null,
            "children": [
                
            ],
            "downs": 0,
            "author_id": 10293874,
            "points": 5,
            "on_album": false,
            "datetime": 1400893175,
            "ups": 5,
            "comment": "I think I must give you this upvote. Yes.",
            "deleted": false,
            "image_id": "iG1kk7a",
            "parent_id": 0
        },
        {
            "id": 229791016,
            "author": "JollyGreen2112",
            "vote": null,
            "album_cover": null,
            "children": [
                
            ],
            "downs": 0,
            "author_id": 4638474,
            "points": 4,
            "on_album": false,
            "datetime": 1400893264,
            "ups": 4,
            "comment": "My man card. It's gone now thanks to this.",
            "deleted": false,
            "image_id": "iG1kk7a",
            "parent_id": 0
        },
        {
            "id": 229971604,
            "author": "arsenalstan",
            "vote": null,
            "album_cover": null,
            "children": [
                {
                    "id": 229973542,
                    "author": "reveta",
                    "vote": null,
                    "album_cover": null,
                    "children": [
                        {
                            "id": 229973728,
                            "author": "arsenalstan",
                            "vote": null,
                            "album_cover": null,
                            "children": [
                                {
                                    "id": 229974142,
                                    "author": "reveta",
                                    "vote": null,
                                    "album_cover": null,
                                    "children": [
                                        {
                                            "id": 229978993,
                                            "author": "laestrella",
                                            "vote": null,
                                            "album_cover": null,
                                            "children": [
                                                {
                                                    "id": 229981276,
                                                    "author": "reveta",
                                                    "vote": null,
                                                    "album_cover": null,
                                                    "children": [
                                                        
                                                    ],
                                                    "downs": 0,
                                                    "author_id": 858486,
                                                    "points": 2,
                                                    "on_album": false,
                                                    "datetime": 1400933511,
                                                    "ups": 2,
                                                    "comment": "Hhaha maybe well see :3 !!",
                                                    "deleted": false,
                                                    "image_id": "iG1kk7a",
                                                    "parent_id": 229978993
                                                }
                                            ],
                                            "downs": 0,
                                            "author_id": 1911630,
                                            "points": 1,
                                            "on_album": false,
                                            "datetime": 1400932740,
                                            "ups": 1,
                                            "comment": "Please make the corgi a spy and perhaps the platypus can be his partner.",
                                            "deleted": false,
                                            "image_id": "iG1kk7a",
                                            "parent_id": 229974142
                                        }
                                    ],
                                    "downs": 0,
                                    "author_id": 858486,
                                    "points": 1,
                                    "on_album": false,
                                    "datetime": 1400931011,
                                    "ups": 1,
                                    "comment": "I can't tell you how much art I worked hours on and posted and it was ripped apart. I'm a truly stunned by this!",
                                    "deleted": false,
                                    "image_id": "iG1kk7a",
                                    "parent_id": 229973728
                                }
                            ],
                            "downs": 0,
                            "author_id": 2914506,
                            "points": 1,
                            "on_album": false,
                            "datetime": 1400930875,
                            "ups": 1,
                            "comment": "Ha I've never been there, so I'll have to take your word for it.",
                            "deleted": false,
                            "image_id": "iG1kk7a",
                            "parent_id": 229973542
                        }
                    ],
                    "downs": 2,
                    "author_id": 858486,
                    "points": 0,
                    "on_album": false,
                    "datetime": 1400930805,
                    "ups": 2,
                    "comment": "Because it's damn hard ottget up here!!! XD!!!!!!",
                    "deleted": false,
                    "image_id": "iG1kk7a",
                    "parent_id": 229971604
                }
            ],
            "downs": 0,
            "author_id": 2914506,
            "points": 3,
            "on_album": false,
            "datetime": 1400930055,
            "ups": 3,
            "comment": "FFS why do people insist on this \"ermagherd I merd it ter the frent perg!\" I want to like this post so much, but... c'mon.",
            "deleted": false,
            "image_id": "iG1kk7a",
            "parent_id": 0
        },
        {
            "id": 229823053,
            "author": "ThomasBankston",
            "vote": null,
            "album_cover": null,
            "children": [
                
            ],
            "downs": 0,
            "author_id": 705765,
            "points": 3,
            "on_album": false,
            "datetime": 1400897847,
            "ups": 3,
            "comment": "http://i.imgur.com/gyit66A.jpg Here it is without the text in case anyone wanted it",
            "deleted": false,
            "image_id": "iG1kk7a",
            "parent_id": 0
        },
        {
            "id": 229821895,
            "author": "TheHappiestQuack",
            "vote": null,
            "album_cover": null,
            "children": [
                
            ],
            "downs": 0,
            "author_id": 6136514,
            "points": 3,
            "on_album": false,
            "datetime": 1400897678,
            "ups": 3,
            "comment": "Next up, penguin and sloth? PLEASE!",
            "deleted": false,
            "image_id": "iG1kk7a",
            "parent_id": 0
        },
        {
            "id": 229808110,
            "author": "c0nman",
            "vote": null,
            "album_cover": null,
            "children": [
                
            ],
            "downs": 0,
            "author_id": 401356,
            "points": 3,
            "on_album": false,
            "datetime": 1400895793,
            "ups": 3,
            "comment": "it looks like the corgi is inappropriately touching that platypus (i am surprisingly okay with this)",
            "deleted": false,
            "image_id": "iG1kk7a",
            "parent_id": 0
        },
        {
            "id": 229792423,
            "author": "stonedwolf",
            "vote": null,
            "album_cover": null,
            "children": [
                
            ],
            "downs": 0,
            "author_id": 11791672,
            "points": 3,
            "on_album": false,
            "datetime": 1400893482,
            "ups": 3,
            "comment": "dat swag...",
            "deleted": false,
            "image_id": "iG1kk7a",
            "parent_id": 0
        },
        {
            "id": 230161465,
            "author": "AlmostHuman2",
            "vote": null,
            "album_cover": null,
            "children": [
                
            ],
            "downs": 0,
            "author_id": 10488571,
            "points": 2,
            "on_album": false,
            "datetime": 1400967292,
            "ups": 2,
            "comment": "OP did deliver ! Good job",
            "deleted": false,
            "image_id": "iG1kk7a",
            "parent_id": 0
        },
        {
            "id": 230020351,
            "author": "SomeoneSneaky",
            "vote": null,
            "album_cover": null,
            "children": [
                
            ],
            "downs": 0,
            "author_id": 1772055,
            "points": 2,
            "on_album": false,
            "datetime": 1400943298,
            "ups": 2,
            "comment": "That is so goddamn adorable.",
            "deleted": false,
            "image_id": "iG1kk7a",
            "parent_id": 0
        },
        {
            "id": 230003653,
            "author": "PotatoSnacker",
            "vote": null,
            "album_cover": null,
            "children": [
                
            ],
            "downs": 0,
            "author_id": 2752795,
            "points": 2,
            "on_album": false,
            "datetime": 1400939718,
            "ups": 2,
            "comment": "Everytime OP Delivers this song comes to mind https://www.youtube.com/watch?v=5Kr4aCUYg8A",
            "deleted": false,
            "image_id": "iG1kk7a",
            "parent_id": 0
        },
        {
            "id": 229999606,
            "author": "tentacleparty",
            "vote": null,
            "album_cover": null,
            "children": [
                {
                    "id": 229999774,
                    "author": "reveta",
                    "vote": null,
                    "album_cover": null,
                    "children": [
                        
                    ],
                    "downs": 0,
                    "author_id": 858486,
                    "points": 1,
                    "on_album": false,
                    "datetime": 1400938741,
                    "ups": 1,
                    "comment": "OMGOSH YES! I can' not GIF dooo it !!! PLEASE omg!",
                    "deleted": false,
                    "image_id": "iG1kk7a",
                    "parent_id": 229999606
                }
            ],
            "downs": 0,
            "author_id": 7029494,
            "points": 2,
            "on_album": false,
            "datetime": 1400938702,
            "ups": 2,
            "comment": "Someone pls make a gif?",
            "deleted": false,
            "image_id": "iG1kk7a",
            "parent_id": 0
        },
        {
            "id": 229996636,
            "author": "onlydreamsnow",
            "vote": null,
            "album_cover": null,
            "children": [
                
            ],
            "downs": 0,
            "author_id": 3312277,
            "points": 2,
            "on_album": false,
            "datetime": 1400937905,
            "ups": 2,
            "comment": "Wow, that's talent!",
            "deleted": false,
            "image_id": "iG1kk7a",
            "parent_id": 0
        },
        {
            "id": 229988779,
            "author": "PlatypusMounter",
            "vote": null,
            "album_cover": null,
            "children": [
                
            ],
            "downs": 0,
            "author_id": 5829733,
            "points": 2,
            "on_album": false,
            "datetime": 1400935834,
            "ups": 2,
            "comment": "That corgi is going to do what I'm famous for.",
            "deleted": false,
            "image_id": "iG1kk7a",
            "parent_id": 0
        },
        {
            "id": 229982284,
            "author": "Heartlyss",
            "vote": null,
            "album_cover": null,
            "children": [
                
            ],
            "downs": 0,
            "author_id": 8975541,
            "points": 2,
            "on_album": false,
            "datetime": 1400933862,
            "ups": 2,
            "comment": "I gotta say, this is the only site on the internet where OP actually delivers... And in such style!",
            "deleted": false,
            "image_id": "iG1kk7a",
            "parent_id": 0
        },
        {
            "id": 229977745,
            "author": "Studoku",
            "vote": null,
            "album_cover": null,
            "children": [
                
            ],
            "downs": 0,
            "author_id": 1863087,
            "points": 2,
            "on_album": false,
            "datetime": 1400932286,
            "ups": 2,
            "comment": "I give this picture a 3/4",
            "deleted": false,
            "image_id": "iG1kk7a",
            "parent_id": 0
        },
        {
            "id": 229972165,
            "author": "graehall",
            "vote": null,
            "album_cover": null,
            "children": [
                
            ],
            "downs": 0,
            "author_id": 5825860,
            "points": 2,
            "on_album": false,
            "datetime": 1400930275,
            "ups": 2,
            "comment": "This is gorgeous, how dainty the corgi is, how fabulous the platypus is. You definitely have a gift for emotional expression. I love this :)",
            "deleted": false,
            "image_id": "iG1kk7a",
            "parent_id": 0
        },
        {
            "id": 229957483,
            "author": "nilee",
            "vote": null,
            "album_cover": null,
            "children": [
                {
                    "id": 229967389,
                    "author": "reveta",
                    "vote": null,
                    "album_cover": null,
                    "children": [
                        {
                            "id": 229968946,
                            "author": "nilee",
                            "vote": null,
                            "album_cover": null,
                            "children": [
                                {
                                    "id": 229969180,
                                    "author": "reveta",
                                    "vote": null,
                                    "album_cover": null,
                                    "children": [
                                        {
                                            "id": 229969312,
                                            "author": "nilee",
                                            "vote": null,
                                            "album_cover": null,
                                            "children": [
                                                {
                                                    "id": 229969357,
                                                    "author": "reveta",
                                                    "vote": null,
                                                    "album_cover": null,
                                                    "children": [
                                                        {
                                                            "id": 229969606,
                                                            "author": "nilee",
                                                            "vote": null,
                                                            "album_cover": null,
                                                            "children": [
                                                                {
                                                                    "id": 229974172,
                                                                    "author": "reveta",
                                                                    "vote": null,
                                                                    "album_cover": null,
                                                                    "children": [
                                                                        {
                                                                            "id": 229974772,
                                                                            "author": "nilee",
                                                                            "vote": null,
                                                                            "album_cover": null,
                                                                            "children": [
                                                                                
                                                                            ],
                                                                            "downs": 0,
                                                                            "author_id": 11441944,
                                                                            "points": 1,
                                                                            "on_album": false,
                                                                            "datetime": 1400931229,
                                                                            "ups": 1,
                                                                            "comment": "(Btw. In my memories which I don\u00B4t have, you\u00B4re the platybus cause you\u00B4re fabulous! :D)",
                                                                            "deleted": false,
                                                                            "image_id": "iG1kk7a",
                                                                            "parent_id": 229974172
                                                                        }
                                                                    ],
                                                                    "downs": 0,
                                                                    "author_id": 858486,
                                                                    "points": 2,
                                                                    "on_album": false,
                                                                    "datetime": 1400931022,
                                                                    "ups": 2,
                                                                    "comment": "XD!!!! LOL",
                                                                    "deleted": false,
                                                                    "image_id": "iG1kk7a",
                                                                    "parent_id": 229969606
                                                                }
                                                            ],
                                                            "downs": 0,
                                                            "author_id": 11441944,
                                                            "points": 1,
                                                            "on_album": false,
                                                            "datetime": 1400929303,
                                                            "ups": 1,
                                                            "comment": "Okay *sniff* at least I have that picture which will always remind me off that time we did not have together as couple *sniff*",
                                                            "deleted": false,
                                                            "image_id": "iG1kk7a",
                                                            "parent_id": 229969357
                                                        }
                                                    ],
                                                    "downs": 0,
                                                    "author_id": 858486,
                                                    "points": 2,
                                                    "on_album": false,
                                                    "datetime": 1400929225,
                                                    "ups": 2,
                                                    "comment": "lol nope sorry!",
                                                    "deleted": false,
                                                    "image_id": "iG1kk7a",
                                                    "parent_id": 229969312
                                                }
                                            ],
                                            "downs": 0,
                                            "author_id": 11441944,
                                            "points": 1,
                                            "on_album": false,
                                            "datetime": 1400929212,
                                            "ups": 1,
                                            "comment": "Nooooooooooo I had plans for us! :D",
                                            "deleted": false,
                                            "image_id": "iG1kk7a",
                                            "parent_id": 229969180
                                        }
                                    ],
                                    "downs": 0,
                                    "author_id": 858486,
                                    "points": 2,
                                    "on_album": false,
                                    "datetime": 1400929156,
                                    "ups": 2,
                                    "comment": "Sorry. I'm already taken by a lovely lady. Don't worry there is some one else out in the world who enjoys drawing cute corgis just for you.",
                                    "deleted": false,
                                    "image_id": "iG1kk7a",
                                    "parent_id": 229968946
                                }
                            ],
                            "downs": 0,
                            "author_id": 11441944,
                            "points": 1,
                            "on_album": false,
                            "datetime": 1400929085,
                            "ups": 1,
                            "comment": "Will....will you marry me <\u00DF ?",
                            "deleted": false,
                            "image_id": "iG1kk7a",
                            "parent_id": 229967389
                        }
                    ],
                    "downs": 0,
                    "author_id": 858486,
                    "points": 2,
                    "on_album": false,
                    "datetime": 1400928450,
                    "ups": 2,
                    "comment": "Wait till I do the whole Waltz sequence :3 I'm going to make it a print <3",
                    "deleted": false,
                    "image_id": "iG1kk7a",
                    "parent_id": 229957483
                }
            ],
            "downs": 0,
            "author_id": 11441944,
            "points": 2,
            "on_album": false,
            "datetime": 1400924800,
            "ups": 2,
            "comment": "This picture has some so much style...I want to hang it up in my living room...",
            "deleted": false,
            "image_id": "iG1kk7a",
            "parent_id": 0
        },
        {
            "id": 229948558,
            "author": "hyasuna",
            "vote": null,
            "album_cover": null,
            "children": [
                
            ],
            "downs": 0,
            "author_id": 1430749,
            "points": 2,
            "on_album": false,
            "datetime": 1400921950,
            "ups": 2,
            "comment": "This is it. Imgur has been won. Everyone go home.",
            "deleted": false,
            "image_id": "iG1kk7a",
            "parent_id": 0
        },
        {
            "id": 229946530,
            "author": "Rocious",
            "vote": null,
            "album_cover": null,
            "children": [
                
            ],
            "downs": 0,
            "author_id": 11088874,
            "points": 2,
            "on_album": false,
            "datetime": 1400921311,
            "ups": 2,
            "comment": "Now draw what their kids would look like.",
            "deleted": false,
            "image_id": "iG1kk7a",
            "parent_id": 0
        },
        {
            "id": 229923961,
            "author": "Andilee",
            "vote": null,
            "album_cover": null,
            "children": [
                
            ],
            "downs": 0,
            "author_id": 4714488,
            "points": 2,
            "on_album": false,
            "datetime": 1400915654,
            "ups": 2,
            "comment": "You made me happy today with this photo! <3",
            "deleted": false,
            "image_id": "iG1kk7a",
            "parent_id": 0
        },
        {
            "id": 229915225,
            "author": "wellfiddledeedee",
            "vote": null,
            "album_cover": null,
            "children": [
                
            ],
            "downs": 0,
            "author_id": 8860134,
            "points": 2,
            "on_album": false,
            "datetime": 1400913665,
            "ups": 2,
            "comment": "Cuz I'm happyyyyy... Clap along if you feel like a platypus in a tutu....",
            "deleted": false,
            "image_id": "iG1kk7a",
            "parent_id": 0
        },
        {
            "id": 229909390,
            "author": "OneADayVitaMan",
            "vote": null,
            "album_cover": null,
            "children": [
                
            ],
            "downs": 0,
            "author_id": 1856795,
            "points": 2,
            "on_album": false,
            "datetime": 1400912480,
            "ups": 2,
            "comment": "Someone needs to draw more, because I certainly want to see more",
            "deleted": false,
            "image_id": "iG1kk7a",
            "parent_id": 0
        },
        {
            "id": 229864831,
            "author": "ElMexingles",
            "vote": null,
            "album_cover": null,
            "children": [
                
            ],
            "downs": 0,
            "author_id": 6802409,
            "points": 2,
            "on_album": false,
            "datetime": 1400904656,
            "ups": 2,
            "comment": "There's a reason that after 3 hours this hasn't been downvoted once. Thank is because it is fucking fantastic OP.",
            "deleted": false,
            "image_id": "iG1kk7a",
            "parent_id": 0
        },
        {
            "id": 229854286,
            "author": "GayCaptainJackSparrow",
            "vote": null,
            "album_cover": null,
            "children": [
                
            ],
            "downs": 0,
            "author_id": 3353732,
            "points": 2,
            "on_album": false,
            "datetime": 1400902914,
            "ups": 2,
            "comment": "I love it! But... http://i.imgur.com/7QtyBbM.gif",
            "deleted": false,
            "image_id": "iG1kk7a",
            "parent_id": 0
        },
        {
            "id": 229827301,
            "author": "Tomkatt",
            "vote": null,
            "album_cover": null,
            "children": [
                
            ],
            "downs": 0,
            "author_id": 8564339,
            "points": 2,
            "on_album": false,
            "datetime": 1400898549,
            "ups": 2,
            "comment": "OP delivered and delivered well. +1 http://i.imgur.com/DgbZ5DPs.jpg",
            "deleted": false,
            "image_id": "iG1kk7a",
            "parent_id": 0
        },
        {
            "id": 229973266,
            "author": "astaen",
            "vote": null,
            "album_cover": null,
            "children": [
                {
                    "id": 229979449,
                    "author": "reveta",
                    "vote": null,
                    "album_cover": null,
                    "children": [
                        
                    ],
                    "downs": 0,
                    "author_id": 858486,
                    "points": 1,
                    "on_album": false,
                    "datetime": 1400932903,
                    "ups": 1,
                    "comment": "PS. I fixed it :3",
                    "deleted": false,
                    "image_id": "iG1kk7a",
                    "parent_id": 229973266
                },
                {
                    "id": 229974685,
                    "author": "reveta",
                    "vote": null,
                    "album_cover": null,
                    "children": [
                        {
                            "id": 229976602,
                            "author": "SexuallyCuriousPenguin",
                            "vote": null,
                            "album_cover": null,
                            "children": [
                                
                            ],
                            "downs": 0,
                            "author_id": 11560588,
                            "points": 1,
                            "on_album": false,
                            "datetime": 1400931889,
                            "ups": 1,
                            "comment": "Many people don't like it because they never get to the front page. Go ahead and celebrate, this is a great post",
                            "deleted": false,
                            "image_id": "iG1kk7a",
                            "parent_id": 229974685
                        },
                        {
                            "id": 229975930,
                            "author": "TysonJarrett",
                            "vote": null,
                            "album_cover": null,
                            "children": [
                                
                            ],
                            "downs": 0,
                            "author_id": 2945761,
                            "points": 1,
                            "on_album": false,
                            "datetime": 1400931660,
                            "ups": 1,
                            "comment": "Reveta you do whatever you want. You earned it ^-^",
                            "deleted": false,
                            "image_id": "iG1kk7a",
                            "parent_id": 229974685
                        }
                    ],
                    "downs": 0,
                    "author_id": 858486,
                    "points": 1,
                    "on_album": false,
                    "datetime": 1400931189,
                    "ups": 1,
                    "comment": "May I ask why not?",
                    "deleted": false,
                    "image_id": "iG1kk7a",
                    "parent_id": 229973266
                }
            ],
            "downs": 1,
            "author_id": 3176771,
            "points": 1,
            "on_album": false,
            "datetime": 1400930713,
            "ups": 2,
            "comment": "This. http://imgur.com/6tU7ddC Please don't do this.",
            "deleted": false,
            "image_id": "iG1kk7a",
            "parent_id": 0
        },
        {
            "id": 230188864,
            "author": "SilkyBunny",
            "vote": null,
            "album_cover": null,
            "children": [
                
            ],
            "downs": 0,
            "author_id": 1963774,
            "points": 1,
            "on_album": false,
            "datetime": 1400971914,
            "ups": 1,
            "comment": "OMG, I SHIP IT <3",
            "deleted": false,
            "image_id": "iG1kk7a",
            "parent_id": 0
        },
        {
            "id": 230182960,
            "author": "WruceBillis",
            "vote": null,
            "album_cover": null,
            "children": [
                
            ],
            "downs": 0,
            "author_id": 10452009,
            "points": 1,
            "on_album": false,
            "datetime": 1400970943,
            "ups": 1,
            "comment": "The Great Platspy",
            "deleted": false,
            "image_id": "iG1kk7a",
            "parent_id": 0
        },
        {
            "id": 230081113,
            "author": "whyyewknow",
            "vote": null,
            "album_cover": null,
            "children": [
                
            ],
            "downs": 0,
            "author_id": 6605264,
            "points": 1,
            "on_album": false,
            "datetime": 1400953740,
            "ups": 1,
            "comment": "Oh...There you are Perry.",
            "deleted": false,
            "image_id": "iG1kk7a",
            "parent_id": 0
        },
        {
            "id": 230053579,
            "author": "Termsofenrampagementobviouslyaworkingtitle",
            "vote": null,
            "album_cover": null,
            "children": [
                
            ],
            "downs": 0,
            "author_id": 1116671,
            "points": 1,
            "on_album": false,
            "datetime": 1400949038,
            "ups": 1,
            "comment": "The early settlers called us duckmoles!!",
            "deleted": false,
            "image_id": "iG1kk7a",
            "parent_id": 0
        },
        {
            "id": 230001559,
            "author": "sillysalamander",
            "vote": null,
            "album_cover": null,
            "children": [
                
            ],
            "downs": 0,
            "author_id": 3565861,
            "points": 1,
            "on_album": false,
            "datetime": 1400939179,
            "ups": 1,
            "comment": "Barbara Manateeee! You are the one for me!",
            "deleted": false,
            "image_id": "iG1kk7a",
            "parent_id": 0
        },
        {
            "id": 230001538,
            "author": "Scaper1812",
            "vote": null,
            "album_cover": null,
            "children": [
                
            ],
            "downs": 0,
            "author_id": 637881,
            "points": 1,
            "on_album": false,
            "datetime": 1400939174,
            "ups": 1,
            "comment": "That is one graceful otter.",
            "deleted": false,
            "image_id": "iG1kk7a",
            "parent_id": 0
        },
        {
            "id": 229992241,
            "author": "WhatWouldBatmanDo",
            "vote": null,
            "album_cover": null,
            "children": [
                {
                    "id": 229995952,
                    "author": "reveta",
                    "vote": null,
                    "album_cover": null,
                    "children": [
                        
                    ],
                    "downs": 0,
                    "author_id": 858486,
                    "points": 2,
                    "on_album": false,
                    "datetime": 1400937717,
                    "ups": 2,
                    "comment": "I've got 4 pages thumb nailed so far <3",
                    "deleted": false,
                    "image_id": "iG1kk7a",
                    "parent_id": 229992241
                }
            ],
            "downs": 0,
            "author_id": 2973540,
            "points": 1,
            "on_album": false,
            "datetime": 1400936740,
            "ups": 1,
            "comment": "I'll just be here waiting for it http://i.imgur.com/pFCu9Zr.gif",
            "deleted": false,
            "image_id": "iG1kk7a",
            "parent_id": 0
        },
        {
            "id": 229990969,
            "author": "shivcakes",
            "vote": null,
            "album_cover": null,
            "children": [
                
            ],
            "downs": 0,
            "author_id": 4908477,
            "points": 1,
            "on_album": false,
            "datetime": 1400936410,
            "ups": 1,
            "comment": "A platypus wearing pearls? I have seen everything.",
            "deleted": false,
            "image_id": "iG1kk7a",
            "parent_id": 0
        },
        {
            "id": 229966159,
            "author": "stallioninthewind",
            "vote": null,
            "album_cover": null,
            "children": [
                
            ],
            "downs": 0,
            "author_id": 9761296,
            "points": 1,
            "on_album": false,
            "datetime": 1400927991,
            "ups": 1,
            "comment": "turnt",
            "deleted": false,
            "image_id": "iG1kk7a",
            "parent_id": 0
        },
        {
            "id": 229944469,
            "author": "TheHallOfTheMountainKing",
            "vote": null,
            "album_cover": null,
            "children": [
                
            ],
            "downs": 0,
            "author_id": 1423593,
            "points": 1,
            "on_album": false,
            "datetime": 1400920744,
            "ups": 1,
            "comment": "I think I fell in love with that corgi.",
            "deleted": false,
            "image_id": "iG1kk7a",
            "parent_id": 0
        },
        {
            "id": 229940119,
            "author": "THEBESTHOSTEVER",
            "vote": null,
            "album_cover": null,
            "children": [
                
            ],
            "downs": 0,
            "author_id": 9761628,
            "points": 1,
            "on_album": false,
            "datetime": 1400919597,
            "ups": 1,
            "comment": "I suggest toad and tiger waltzing",
            "deleted": false,
            "image_id": "iG1kk7a",
            "parent_id": 0
        },
        {
            "id": 229934383,
            "author": "theplatypusSays",
            "vote": null,
            "album_cover": null,
            "children": [
                
            ],
            "downs": 0,
            "author_id": 11636401,
            "points": 1,
            "on_album": false,
            "datetime": 1400918155,
            "ups": 1,
            "comment": "Oh! My!",
            "deleted": false,
            "image_id": "iG1kk7a",
            "parent_id": 0
        },
        {
            "id": 229925698,
            "author": "Platypuspolice",
            "vote": null,
            "album_cover": null,
            "children": [
                
            ],
            "downs": 0,
            "author_id": 5439417,
            "points": 1,
            "on_album": false,
            "datetime": 1400916027,
            "ups": 1,
            "comment": "Sorta relevant?",
            "deleted": false,
            "image_id": "iG1kk7a",
            "parent_id": 0
        },
        {
            "id": 229918648,
            "author": "KRISTENFRESH1",
            "vote": null,
            "album_cover": null,
            "children": [
                
            ],
            "downs": 0,
            "author_id": 860288,
            "points": 1,
            "on_album": false,
            "datetime": 1400914449,
            "ups": 1,
            "comment": "I need almosthuman2 to see this!!! Where are you?!?!?",
            "deleted": false,
            "image_id": "iG1kk7a",
            "parent_id": 0
        },
        {
            "id": 229915648,
            "author": "96inox",
            "vote": null,
            "album_cover": null,
            "children": [
                
            ],
            "downs": 0,
            "author_id": 11215393,
            "points": 1,
            "on_album": false,
            "datetime": 1400913765,
            "ups": 1,
            "comment": "Cha Cha or Tango next!",
            "deleted": false,
            "image_id": "iG1kk7a",
            "parent_id": 0
        },
        {
            "id": 229915189,
            "author": "DKTSMTH",
            "vote": null,
            "album_cover": null,
            "children": [
                
            ],
            "downs": 0,
            "author_id": 1898992,
            "points": 1,
            "on_album": false,
            "datetime": 1400913661,
            "ups": 1,
            "comment": "Can you draw me a bug.",
            "deleted": false,
            "image_id": "iG1kk7a",
            "parent_id": 0
        },
        {
            "id": 229914601,
            "author": "Minnesoooota",
            "vote": null,
            "album_cover": null,
            "children": [
                
            ],
            "downs": 0,
            "author_id": 8330229,
            "points": 1,
            "on_album": false,
            "datetime": 1400913531,
            "ups": 1,
            "comment": "It's beautiful. *single tear*",
            "deleted": false,
            "image_id": "iG1kk7a",
            "parent_id": 0
        },
        {
            "id": 229914568,
            "author": "wellfiddledeedee",
            "vote": null,
            "album_cover": null,
            "children": [
                
            ],
            "downs": 0,
            "author_id": 8860134,
            "points": 1,
            "on_album": false,
            "datetime": 1400913527,
            "ups": 1,
            "comment": "They must dip reeeeaaaal low since they're so short.",
            "deleted": false,
            "image_id": "iG1kk7a",
            "parent_id": 0
        },
        {
            "id": 229914355,
            "author": "wellfiddledeedee",
            "vote": null,
            "album_cover": null,
            "children": [
                
            ],
            "downs": 0,
            "author_id": 8860134,
            "points": 1,
            "on_album": false,
            "datetime": 1400913481,
            "ups": 1,
            "comment": "I must dance!",
            "deleted": false,
            "image_id": "iG1kk7a",
            "parent_id": 0
        },
        {
            "id": 229914283,
            "author": "wellfiddledeedee",
            "vote": null,
            "album_cover": null,
            "children": [
                
            ],
            "downs": 0,
            "author_id": 8860134,
            "points": 1,
            "on_album": false,
            "datetime": 1400913462,
            "ups": 1,
            "comment": "I... I love it!",
            "deleted": false,
            "image_id": "iG1kk7a",
            "parent_id": 0
        },
        {
            "id": 229910932,
            "author": "Daggaroth",
            "vote": null,
            "album_cover": null,
            "children": [
                
            ],
            "downs": 0,
            "author_id": 5652104,
            "points": 1,
            "on_album": false,
            "datetime": 1400912782,
            "ups": 1,
            "comment": "I would like to request Two T-Rexes Sword Fighting!",
            "deleted": false,
            "image_id": "iG1kk7a",
            "parent_id": 0
        },
        {
            "id": 229909870,
            "author": "doesanyonehavethisusername",
            "vote": null,
            "album_cover": null,
            "children": [
                
            ],
            "downs": 0,
            "author_id": 10897009,
            "points": 1,
            "on_album": false,
            "datetime": 1400912571,
            "ups": 1,
            "comment": "You should have an entire series of these drawings! Can you do an Ostrich and Donkey on lunch break at a blue collar - factory job?",
            "deleted": false,
            "image_id": "iG1kk7a",
            "parent_id": 0
        },
        {
            "id": 229909042,
            "author": "BreaphGoat82",
            "vote": null,
            "album_cover": null,
            "children": [
                
            ],
            "downs": 0,
            "author_id": 10625122,
            "points": 1,
            "on_album": false,
            "datetime": 1400912413,
            "ups": 1,
            "comment": "Elegance and pearls, sigh.",
            "deleted": false,
            "image_id": "iG1kk7a",
            "parent_id": 0
        },
        {
            "id": 229908628,
            "author": "BadGrammerNazi",
            "vote": null,
            "album_cover": null,
            "children": [
                
            ],
            "downs": 0,
            "author_id": 9896306,
            "points": 1,
            "on_album": false,
            "datetime": 1400912334,
            "ups": 1,
            "comment": "Why isn't the bitch the girl",
            "deleted": false,
            "image_id": "iG1kk7a",
            "parent_id": 0
        },
        {
            "id": 229908469,
            "author": "Shadowfallen",
            "vote": null,
            "album_cover": null,
            "children": [
                
            ],
            "downs": 0,
            "author_id": 3630770,
            "points": 1,
            "on_album": false,
            "datetime": 1400912304,
            "ups": 1,
            "comment": "Are you taking requests?",
            "deleted": false,
            "image_id": "iG1kk7a",
            "parent_id": 0
        },
        {
            "id": 229897093,
            "author": "god007",
            "vote": null,
            "album_cover": null,
            "children": [
                {
                    "id": 229973749,
                    "author": "reveta",
                    "vote": null,
                    "album_cover": null,
                    "children": [
                        
                    ],
                    "downs": 0,
                    "author_id": 858486,
                    "points": 1,
                    "on_album": false,
                    "datetime": 1400930882,
                    "ups": 1,
                    "comment": "Wish granted, Thank you so much for the wonderful name!",
                    "deleted": false,
                    "image_id": "iG1kk7a",
                    "parent_id": 229897093
                }
            ],
            "downs": 0,
            "author_id": 9386751,
            "points": 1,
            "on_album": false,
            "datetime": 1400910128,
            "ups": 1,
            "comment": "I bet, the platypus is called Matilda.",
            "deleted": false,
            "image_id": "iG1kk7a",
            "parent_id": 0
        },
        {
            "id": 229874197,
            "author": "AureliaVerity",
            "vote": null,
            "album_cover": null,
            "children": [
                
            ],
            "downs": 0,
            "author_id": 4905018,
            "points": 1,
            "on_album": false,
            "datetime": 1400906233,
            "ups": 1,
            "comment": "Of all the things to cheer me up after a bad day, i didn't think this would be it when i loged on",
            "deleted": false,
            "image_id": "iG1kk7a",
            "parent_id": 0
        },
        {
            "id": 229873354,
            "author": "QuantumShittingThroughTheNthDimension",
            "vote": null,
            "album_cover": null,
            "children": [
                
            ],
            "downs": 0,
            "author_id": 3608897,
            "points": 1,
            "on_album": false,
            "datetime": 1400906093,
            "ups": 1,
            "comment": "Oh my god. We need more. You should draw whatever the next top-comment is!",
            "deleted": false,
            "image_id": "iG1kk7a",
            "parent_id": 0
        },
        {
            "id": 230112580,
            "author": "HitlerEatingABanana",
            "vote": null,
            "album_cover": null,
            "children": [
                
            ],
            "downs": 1,
            "author_id": 11151019,
            "points": 0,
            "on_album": false,
            "datetime": 1400959235,
            "ups": 1,
            "comment": "What my username says",
            "deleted": false,
            "image_id": "iG1kk7a",
            "parent_id": 0
        },
        {
            "id": 230025394,
            "author": "matt39900",
            "vote": null,
            "album_cover": null,
            "children": [
                
            ],
            "downs": 1,
            "author_id": 6885758,
            "points": 0,
            "on_album": false,
            "datetime": 1400944238,
            "ups": 1,
            "comment": "Even his eminent poop has a shadow!",
            "deleted": false,
            "image_id": "iG1kk7a",
            "parent_id": 0
        },
        {
            "id": 229910512,
            "author": "LeatherjacketBird245",
            "vote": null,
            "album_cover": null,
            "children": [
                
            ],
            "downs": 2,
            "author_id": 11310643,
            "points": -1,
            "on_album": false,
            "datetime": 1400912699,
            "ups": 1,
            "comment": "repost",
            "deleted": false,
            "image_id": "iG1kk7a",
            "parent_id": 0
        }
    ],
    "success": true
}